osma/__init__.py
osma/aggregators/__init__.py
osma/aggregators/jekyll.py
osma/api.py
osma/cli.py
osma/sources/__init__.py
osma/sources/newsapi.py
osma/sources/reddit.py
osma/sources/twitter.py
osma-0.1.1.dist-info/entry_points.txt
osma-0.1.1.dist-info/WHEEL
osma-0.1.1.dist-info/METADATA
osma-0.1.1.dist-info/RECORD
