Metadata-Version: 2.1
Name: osma
Version: 0.1.1
Summary: 
Author: Mihails Delmans
Author-email: m.delmans@gmail.com
Requires-Python: >=3.9,<4.0
Classifier: Programming Language :: Python :: 3
Classifier: Programming Language :: Python :: 3.9
Requires-Dist: click (>=8.0.3,<9.0.0)
Requires-Dist: favicon (>=0.7.0,<0.8.0)
Requires-Dist: loguru (>=0.5.3,<0.6.0)
Requires-Dist: newsapi-python (>=0.2.6,<0.3.0)
Requires-Dist: praw (>=7.5.0,<8.0.0)
Requires-Dist: python-frontmatter (>=1.0.0,<2.0.0)
Requires-Dist: toml (>=0.10.2,<0.11.0)
Requires-Dist: tweepy (>=4.4.0,<5.0.0)
